topsis_palak/__init__.py
topsis_palak/topsis.py
Topsis_Palak_102216032-0.1.1.dist-info/METADATA
Topsis_Palak_102216032-0.1.1.dist-info/WHEEL
Topsis_Palak_102216032-0.1.1.dist-info/entry_points.txt
Topsis_Palak_102216032-0.1.1.dist-info/top_level.txt
Topsis_Palak_102216032-0.1.1.dist-info/RECORD
